nops_cloudtrail/__init__.py
nops_cloudtrail/bucket.py
nops_cloudtrail/data_types.py
nops_cloudtrail/exceptions.py
nops_cloudtrail/fetcher.py
nops_cloudtrail/tests/__init__.py
nops_cloudtrail/tests/conftest.py
nops_cloudtrail/tests/test_fetcher.py
nops_cloudtrail/tests/test_utils.py
nops_cloudtrail/utils.py
nops_cloudtrail-0.3.2.dist-info/WHEEL
nops_cloudtrail-0.3.2.dist-info/METADATA
nops_cloudtrail-0.3.2.dist-info/RECORD
