Metadata-Version: 2.1
Name: nops-cloudtrail
Version: 0.3.2
Summary: Pull cloudtrail logs from S3 bucket.
Author: nOps Engineers
Author-email: eng@nops.io
Classifier: Programming Language :: Python :: 2
Classifier: Programming Language :: Python :: 2.7
Classifier: Programming Language :: Python :: 3
Classifier: Programming Language :: Python :: 3.4
Classifier: Programming Language :: Python :: 3.5
Classifier: Programming Language :: Python :: 3.6
Classifier: Programming Language :: Python :: 3.7
Classifier: Programming Language :: Python :: 3.8
Classifier: Programming Language :: Python :: 3.9
Classifier: Programming Language :: Python :: 3.10
Classifier: Programming Language :: Python :: 3.11
Requires-Dist: boto3 (>=1.17.102)
Requires-Dist: ijson (>=3.1)
Requires-Dist: orjson (>=3.6.9)
Requires-Dist: pydantic (>=1.8.0)
Requires-Dist: pyrsistent (>=0.17.3)
Requires-Dist: python-dateutil (>=2.8.2)
